lnmc.py
lnmc-1.4.0.dist-info/LICENSE
lnmc-1.4.0.dist-info/METADATA
lnmc-1.4.0.dist-info/WHEEL
lnmc-1.4.0.dist-info/entry_points.txt
lnmc-1.4.0.dist-info/top_level.txt
lnmc-1.4.0.dist-info/RECORD
