Metadata-Version: 2.1
Name: lnmc
Version: 1.4.0
Summary: Allows to create symbolic link in batches from a YAML file and consolidate them in a specific directory.
Author-email: Daniel Luque <danielluque14@gmail.com>
License: AGPLv3+
Project-URL: Source Code, https://github.com/LuqueDaniel/lnmc
Project-URL: Issue Tracker, https://github.com/LuqueDaniel/lnmc/issues
Project-URL: Documentation, https://github.com/LuqueDaniel/lnmc/blob/master/README.md
Keywords: linux,windows,devops,sysadmin,batches,symlink,command-line-tool,cli
Classifier: Development Status :: 5 - Production/Stable
Classifier: Intended Audience :: Developers
Classifier: Intended Audience :: System Administrators
Classifier: License :: OSI Approved :: GNU Affero General Public License v3 or later (AGPLv3+)
Classifier: Operating System :: Microsoft :: Windows
Classifier: Operating System :: POSIX :: Linux
Classifier: Operating System :: MacOS
Classifier: Programming Language :: Python :: 3
Classifier: Programming Language :: Python :: 3.8
Classifier: Programming Language :: Python :: 3.9
Classifier: Programming Language :: Python :: 3.10
Classifier: Programming Language :: Python :: 3.11
Classifier: Programming Language :: Python :: 3.12
Classifier: Topic :: System :: Systems Administration
Classifier: Topic :: Utilities
Requires-Python: >=3.8
License-File: LICENSE
Requires-Dist: Click ~=8.1.7
Requires-Dist: PyYAML ~=6.0.0
Provides-Extra: dev
Requires-Dist: pre-commit ==3.5.0 ; extra == 'dev'
Requires-Dist: black ==23.12.1 ; extra == 'dev'
Requires-Dist: isort ~=5.13.2 ; extra == 'dev'
Requires-Dist: ruff >=0.1.9 ; extra == 'dev'
Requires-Dist: mypy ~=1.8.0 ; extra == 'dev'
Requires-Dist: pytest ~=7.4.3 ; extra == 'dev'
Requires-Dist: pytest-cov ~=4.1.0 ; extra == 'dev'
Requires-Dist: types-PyYAML ~=6.0.0 ; extra == 'dev'
